pubg_client/__init__.py
pubg_client/_api.py
pubg_client/_client.py
pubg_client/endpoints/__init__.py
pubg_client/endpoints/_base.py
pubg_client/endpoints/match.py
pubg_client/endpoints/status.py
pubg_client/models/__init__.py
pubg_client/models/_base.py
pubg_client/models/asset.py
pubg_client/models/match.py
pubg_client/models/participant.py
pubg_client/models/roster.py
pubg_client/models/status.py
pubg_client-0.1.4.dist-info/DESCRIPTION.rst
pubg_client-0.1.4.dist-info/METADATA
pubg_client-0.1.4.dist-info/RECORD
pubg_client-0.1.4.dist-info/WHEEL
pubg_client-0.1.4.dist-info/metadata.json
pubg_client-0.1.4.dist-info/top_level.txt
